[{"id":46341,"name":"\u5317\u4ed1\u533a"},{"id":1224,"name":"\u6148\u6eaa\u5e02"},{"id":1226,"name":"\u5949\u5316\u533a"},{"id":4253,"name":"\u9ad8\u65b0\u79d1\u6280\u5f00\u53d1\u533a"},{"id":3412,"name":"\u6d77\u66d9\u533a"},{"id":46344,"name":"\u6c5f\u5317\u533a"},{"id":3413,"name":"\u6c5f\u4e1c\u533a"},{"id":1227,"name":"\u5b81\u6d77\u53bf"},{"id":1228,"name":"\u8c61\u5c71\u53bf"},{"id":46343,"name":"\u911e\u5dde\u533a"},{"id":46345,"name":"\u4f59\u59da\u5e02"},{"id":46342,"name":"\u9547\u6d77\u533a"}]