[{"id":1090,"name":"\u6ee8\u5dde\u5e02"},{"id":1060,"name":"\u5fb7\u5dde\u5e02"},{"id":1025,"name":"\u4e1c\u8425\u5e02"},{"id":1099,"name":"\u83cf\u6cfd\u5e02"},{"id":2900,"name":"\u6d4e\u5b81\u5e02"},{"id":1000,"name":"\u6d4e\u5357\u5e02"},{"id":1081,"name":"\u804a\u57ce\u5e02"},{"id":1058,"name":"\u83b1\u829c\u5e02"},{"id":1072,"name":"\u4e34\u6c82\u5e02"},{"id":1007,"name":"\u9752\u5c9b\u5e02"},{"id":1108,"name":"\u65e5\u7167\u5e02"},{"id":1112,"name":"\u6cf0\u5b89\u5e02"},{"id":1032,"name":"\u6f4d\u574a\u5e02"},{"id":1053,"name":"\u5a01\u6d77\u5e02"},{"id":1042,"name":"\u70df\u53f0\u5e02"},{"id":1022,"name":"\u67a3\u5e84\u5e02"},{"id":1016,"name":"\u6dc4\u535a\u5e02"}]