[{"id":26559,"name":"\u516b\u6c5f\u4e61"},{"id":26555,"name":"\u77f3\u9a6c\u9547"},{"id":26572,"name":"\u5b98\u5c71\u6797\u573a"},{"id":26552,"name":"\u53e4\u53bf\u9547"},{"id":26569,"name":"\u541b\u57e0\u4e61"},{"id":26550,"name":"\u5751\u7530\u9547"},{"id":26571,"name":"\u7f57\u94fa\u57a6\u6b96\u573a"},{"id":26557,"name":"\u9f99\u5188\u7572\u65cf\u4e61"},{"id":26561,"name":"\u9e7f\u5188\u4e61"},{"id":26562,"name":"\u4e03\u90fd\u4e61"},{"id":26556,"name":"\u6c99\u6eaa\u9547"},{"id":26568,"name":"\u4e0a\u56fa\u4e61"},{"id":26565,"name":"\u4e0a\u6eaa\u4e61"},{"id":26567,"name":"\u4e09\u574a\u4e61"},{"id":26560,"name":"\u6f6d\u57ce\u4e61"},{"id":26566,"name":"\u6f6d\u5934\u4e61"},{"id":26563,"name":"\u9676\u5858\u4e61"},{"id":26554,"name":"\u85e4\u7530\u9547"},{"id":40865,"name":"\u53bf\u57ce\u5185"},{"id":26551,"name":"\u6cbf\u9642\u9547"},{"id":26553,"name":"\u7476\u7530\u9547"},{"id":26570,"name":"\u6c38\u4e30\u53bf\u5de5\u4e1a\u56ed\u533a"},{"id":26564,"name":"\u4e2d\u6751\u4e61"},{"id":26558,"name":"\u4f50\u9f99\u4e61"},{"id":26549,"name":"\u6069\u6c5f\u9547"}]