[{"id":28529,"name":"\u767d\u6cb3\u7267\u573a"},{"id":28514,"name":"\u73ed\u4f51\u4e61"},{"id":28527,"name":"\u5305\u5ea7\u4e61"},{"id":28525,"name":"\u5df4\u897f\u4e61"},{"id":28521,"name":"\u5d07\u5c14\u4e61"},{"id":28512,"name":"\u8fbe\u624e\u5bfa\u9547"},{"id":28520,"name":"\u51bb\u5217\u4e61"},{"id":28517,"name":"\u7ea2\u661f\u9547"},{"id":28530,"name":"\u8f96\u66fc\u9547"},{"id":28524,"name":"\u964d\u624e\u4e61"},{"id":28518,"name":"\u9ea6\u6eaa\u4e61"},{"id":28519,"name":"\u5ae9\u54c7\u4e61"},{"id":28526,"name":"\u6c42\u5409\u4e61"},{"id":28522,"name":"\u70ed\u5c14\u4e61"},{"id":28513,"name":"\u5510\u514b\u9547"},{"id":40285,"name":"\u53bf\u57ce\u5185"},{"id":28523,"name":"\u5360\u54c7\u4e61"},{"id":28528,"name":"\u963f\u897f\u9547"}]