[{"name":"\u5c4f\u8fb9\u82d7\u65cf\u81ea\u6cbb\u53bf","id":2330},{"name":"\u77f3\u5c4f\u53bf","id":2328},{"name":"\u4e2a\u65e7\u5e02","id":2319},{"name":"\u7ea2\u6cb3\u53bf","id":2322},{"name":"\u6cb3\u53e3\u7476\u65cf\u81ea\u6cbb\u53bf","id":2331},{"name":"\u5efa\u6c34\u53bf","id":2326},{"name":"\u91d1\u5e73\u82d7\u65cf\u7476\u65cf\u50a3\u65cf\u81ea\u6cbb\u53bf","id":2329},{"name":"\u5f00\u8fdc\u5e02","id":2320},{"name":"\u7eff\u6625\u53bf","id":2323},{"name":"\u6cf8\u897f\u53bf","id":2325},{"name":"\u5f25\u52d2\u5e02","id":2321},{"name":"\u8499\u81ea\u5e02","id":2324},{"name":"\u5143\u9633\u53bf","id":2327}]