[{"id":3780,"name":"\u516b\u6240\u9547"},{"id":3784,"name":"\u677f\u6865\u9547"},{"id":3782,"name":"\u5927\u7530\u9547"},{"id":12781,"name":"\u4e1c\u65b9\u534e\u4fa8\u519c\u573a"},{"id":3781,"name":"\u4e1c\u6cb3\u9547"},{"id":12780,"name":"\u5e7f\u575d\u519c\u573a"},{"id":3783,"name":"\u611f\u57ce\u9547"},{"id":3789,"name":"\u6c5f\u8fb9\u4e61"},{"id":3786,"name":"\u56db\u66f4\u9547"},{"id":3785,"name":"\u4e09\u5bb6\u9547"},{"id":54493,"name":"\u4e1c\u65b9\u519c\u573a"},{"id":3788,"name":"\u5929\u5b89\u4e61"},{"id":3787,"name":"\u65b0\u9f99\u9547"}]