[{"name":"\u57ce\u533a","id":39414},{"name":"\u5927\u6da7\u4e61","id":14077},{"name":"\u9ad8\u5bb6\u4f1a\u4e61","id":14073},{"name":"\u5c9a\u6f2a\u9547","id":15007},{"name":"\u674e\u5bb6\u6c9f\u4e61","id":14072},{"name":"\u6c34\u5cea\u8d2f\u4e61","id":15009},{"name":"\u795e\u5802\u576a\u4e61","id":15008},{"name":"\u5b8b\u5bb6\u6c9f\u4e61","id":15010},{"name":"\u4e09\u4e95\u9547","id":14071},{"name":"\u738b\u5bb6\u5c94\u4e61","id":14075},{"name":"\u6e29\u6cc9\u4e61","id":15011},{"name":"\u897f\u8c79\u5cea\u4e61","id":14074},{"name":"\u9633\u576a\u4e61","id":14076}]