[{"id":12857,"name":"\u575d\u6cb3\u9547"},{"id":52767,"name":"\u57ce\u533a"},{"id":12847,"name":"\u8328\u6c9f\u9547"},{"id":12840,"name":"\u5927\u6cb3\u9547"},{"id":12856,"name":"\u77f3\u68af\u9547"},{"id":12845,"name":"\u77f3\u8f6c\u9547"},{"id":12831,"name":"\u5927\u540c\u9547"},{"id":12829,"name":"\u5927\u7af9\u56ed\u9547"},{"id":12866,"name":"\u4e1c\u9547\u4e61"},{"id":12849,"name":"\u5bcc\u5f3a\u4e61"},{"id":60703,"name":"\u65e9\u9633\u9547"},{"id":60518,"name":"\u7530\u575d\u9547"},{"id":12855,"name":"\u5173\u5bb6\u9547"},{"id":12835,"name":"\u5173\u5e99\u9547"},{"id":12850,"name":"\u89c2\u97f3\u6cb3\u9547"},{"id":12852,"name":"\u5171\u8fdb\u9547"},{"id":12869,"name":"\u82b1\u56ed\u4e61"},{"id":12830,"name":"\u6052\u53e3\u9547"},{"id":12834,"name":"\u6cb3\u897f\u9547"},{"id":12846,"name":"\u6d2a\u5c71\u9547"},{"id":12833,"name":"\u5efa\u6c11\u8857\u9053"},{"id":56604,"name":"\u6c5f\u5317\u8857\u9053"},{"id":12841,"name":"\u5409\u6cb3\u9547"},{"id":12868,"name":"\u8346\u6cb3\u4e61"},{"id":12844,"name":"\u6d41\u6c34\u9547"},{"id":56605,"name":"\u8001\u57ce\u8857\u9053"},{"id":12828,"name":"\u6885\u5b50\u94fa\u9547"},{"id":12865,"name":"\u725b\u8e44\u9547"},{"id":12858,"name":"\u5357\u6eaa\u4e61"},{"id":12851,"name":"\u524d\u8fdb\u4e61"},{"id":12843,"name":"\u53cc\u9f99\u9547"},{"id":12860,"name":"\u53cc\u6eaa\u9547"},{"id":12867,"name":"\u6c99\u575d\u4e61"},{"id":12839,"name":"\u6c88\u575d\u9547"},{"id":12870,"name":"\u8c2d\u575d\u9547"},{"id":12832,"name":"\u4e94\u91cc\u9547"},{"id":12853,"name":"\u53bf\u6cb3\u4e61"},{"id":12864,"name":"\u53bf\u6cb3\u9547"},{"id":12837,"name":"\u53f6\u576a\u9547"},{"id":12862,"name":"\u9999\u5c71\u4e61"},{"id":12861,"name":"\u65b0\u575d\u9547"},{"id":56606,"name":"\u65b0\u57ce\u8857\u9053"},{"id":12863,"name":"\u664f\u575d\u9547"},{"id":12854,"name":"\u8fce\u98ce\u4e61"},{"id":12842,"name":"\u701b\u6e56\u9547"},{"id":12859,"name":"\u7389\u5c9a\u4e61"},{"id":12848,"name":"\u8fd0\u6eaa\u4e61"},{"id":12836,"name":"\u5f20\u6ee9\u9547"},{"id":12838,"name":"\u4e2d\u539f\u9547"},{"id":56607,"name":"\u7d2b\u8346\u9547"}]