[{"name":"KANAZAWA","id":63966},{"name":"KAHOKU","id":63981},{"name":"WAJIMA","id":63980},{"name":"SUZU","id":63979},{"name":"HOSU-GUN","id":63978},{"name":"NANAO","id":63977},{"name":"HAKUI-GUN","id":63976},{"name":"HAKUI","id":63975},{"name":"NOMI-GUN","id":63974},{"name":"NOMI","id":63973},{"name":"KOMATSU","id":63972},{"name":"KAGA","id":63971},{"name":"NONOICHI","id":63970},{"name":"ISHIKAWA-GUN","id":63969},{"name":"HAKUSAN","id":63968},{"name":"KAHOKU-GUN","id":63967},{"name":"KASHIMA-GUN","id":63982}]