[{"name":"TOKUSHIMA","id":63797},{"name":"YOSHINOGAWA","id":63811},{"name":"KAIFU-GUN","id":63810},{"name":"KOMATSUSHIMA","id":63809},{"name":"NAKA-GUN","id":63808},{"name":"ANAN","id":63807},{"name":"KATSURA-GUN","id":63806},{"name":"MYODO-GUN","id":63805},{"name":"MYOZAI-GUN","id":63804},{"name":"MIYOSHI-GUN","id":63803},{"name":"MIYOSHI","id":63802},{"name":"MIMA","id":63801},{"name":"AWA","id":63800},{"name":"NARUTO","id":63799},{"name":"ITANO-GUN","id":63798},{"name":"MIMA-GUN","id":63812}]