[{"id":454,"name":"\u9e64\u58c1\u5e02"},{"id":482,"name":"\u8bb8\u660c\u5e02"},{"id":446,"name":"\u7126\u4f5c\u5e02"},{"id":2780,"name":"\u6d4e\u6e90\u5e02"},{"id":420,"name":"\u5f00\u5c01\u5e02"},{"id":489,"name":"\u6f2f\u6cb3\u5e02"},{"id":427,"name":"\u6d1b\u9633\u5e02"},{"id":502,"name":"\u5357\u9633\u5e02"},{"id":438,"name":"\u5e73\u9876\u5c71\u5e02"},{"id":475,"name":"\u6fee\u9633\u5e02"},{"id":517,"name":"\u5546\u4e18\u5e02"},{"id":495,"name":"\u4e09\u95e8\u5ce1\u5e02"},{"id":549,"name":"\u4fe1\u9633\u5e02"},{"id":458,"name":"\u65b0\u4e61\u5e02"},{"id":412,"name":"\u90d1\u5dde\u5e02"},{"id":538,"name":"\u9a7b\u9a6c\u5e97\u5e02"},{"id":527,"name":"\u5468\u53e3\u5e02"},{"id":468,"name":"\u5b89\u9633\u5e02"}]