[{"name":"\u516b\u6bb5\u5de5\u4e1a\u56ed\u533a","id":4228},{"name":"\u4e30\u53bf","id":917},{"name":"\u9f13\u697c\u533a","id":23686},{"name":"\u8d3e\u6c6a\u533a","id":3388},{"name":"\u91d1\u5c71\u6865\u5f00\u53d1\u533a","id":4223},{"name":"\u6c9b\u53bf","id":916},{"name":"\u90b3\u5dde\u5e02","id":23687},{"name":"\u6cc9\u5c71\u533a","id":23688},{"name":"\u7762\u5b81\u53bf","id":915},{"name":"\u94dc\u5c71\u7ecf\u6d4e\u6280\u672f\u5f00\u53d1\u533a","id":4224},{"name":"\u94dc\u5c71\u533a","id":914},{"name":"\u65b0\u6c82\u5e02","id":23689},{"name":"\u4e91\u9f99\u533a","id":23690}]