[{"name":"\u516b\u5de8\u9547","id":23700},{"name":"\u516b\u6ee9\u9547","id":23696},{"name":"\u6ee8\u6dee\u9547","id":23701},{"name":"\u6ee8\u6d77\u6e2f\u9547","id":23691},{"name":"\u57ce\u533a","id":39564},{"name":"\u9648\u6d9b\u9547","id":23694},{"name":"\u8521\u6865\u9547","id":23697},{"name":"\u4e1c\u574e\u9547","id":23699},{"name":"\u754c\u724c\u9547","id":23698},{"name":"\u6ee8\u6d77\u6e2f\u7ecf\u6d4e\u533a","id":60521},{"name":"\u5f00\u53d1\u533a\u6cbf\u6d77\u5de5\u4e1a\u56ed","id":60338},{"name":"\u5929\u573a\u9547","id":23703},{"name":"\u5f00\u53d1\u533a\u5de5\u4e1a\u56ed","id":60490},{"name":"\u73b0\u4ee3\u519c\u4e1a\u4ea7\u4e1a\u56ed\u533a","id":60374},{"name":"\u901a\u6986\u9547","id":23692},{"name":"\u4e94\u6c5b\u9547","id":23693},{"name":"\u65b0\u6ee9\u76d0\u573a","id":23695},{"name":"\u6b63\u7ea2\u9547","id":23702}]